add_header_mv-0.3.dist-info/METADATA
add_header_mv-0.3.dist-info/RECORD
add_header_mv-0.3.dist-info/WHEEL
add_header_mv-0.3.dist-info/entry_points.txt
add_header_mv-0.3.dist-info/top_level.txt
hammal/__init__.py
hammal/hammal.py
