Metadata-Version: 2.1
Name: add-header-mv
Version: 0.3
Summary: Add header to files and move them
Home-page: https://github.com/tdkihrr/add-header-mv
Author: tdkihrr
Author-email: huanghezhao@outlook.com
License: MIT
Keywords: tool
Platform: any
Requires-Python: >=3.4.0
